odoo/addons/auth_saml_environment/README.rst
odoo/addons/auth_saml_environment/__init__.py
odoo/addons/auth_saml_environment/__manifest__.py
odoo/addons/auth_saml_environment/controllers/__init__.py
odoo/addons/auth_saml_environment/controllers/main.py
odoo/addons/auth_saml_environment/i18n/auth_saml_environment.pot
odoo/addons/auth_saml_environment/i18n/ca.po
odoo/addons/auth_saml_environment/models/__init__.py
odoo/addons/auth_saml_environment/models/auth_saml_provider.py
odoo/addons/auth_saml_environment/readme/CONFIGURE.rst
odoo/addons/auth_saml_environment/readme/CONTRIBUTORS.rst
odoo/addons/auth_saml_environment/readme/DESCRIPTION.rst
odoo/addons/auth_saml_environment/readme/INSTALL.rst
odoo/addons/auth_saml_environment/readme/ROADMAP.rst
odoo/addons/auth_saml_environment/readme/USAGE.rst
odoo/addons/auth_saml_environment/static/description/icon.png
odoo/addons/auth_saml_environment/static/description/index.html
odoo/addons/auth_saml_environment/tests/__init__.py
odoo/addons/auth_saml_environment/tests/test_environment_variable.py
odoo/addons/auth_saml_environment/views/saml_provider_view.xml
odoo14_addon_auth_saml_environment-14.0.1.0.2.dist-info/METADATA
odoo14_addon_auth_saml_environment-14.0.1.0.2.dist-info/WHEEL
odoo14_addon_auth_saml_environment-14.0.1.0.2.dist-info/top_level.txt
odoo14_addon_auth_saml_environment-14.0.1.0.2.dist-info/RECORD
